README.md
pyproject.toml
setup.cfg
setup.py
cms_client/__init__.py
cms_client/api_client.py
cms_client/api_response.py
cms_client/configuration.py
cms_client/exceptions.py
cms_client/py.typed
cms_client/rest.py
cms_client.egg-info/PKG-INFO
cms_client.egg-info/SOURCES.txt
cms_client.egg-info/dependency_links.txt
cms_client.egg-info/requires.txt
cms_client.egg-info/top_level.txt
cms_client/api/__init__.py
cms_client/api/annotations_api.py
cms_client/api/authentication_api.py
cms_client/api/evaluating_api.py
cms_client/api/generate_text_based_on_the_input_prompt_api.py
cms_client/api/generative_api.py
cms_client/api/metadata_api.py
cms_client/api/open_ai_compatible_api.py
cms_client/api/redaction_api.py
cms_client/api/rendering_api.py
cms_client/api/training_api.py
cms_client/models/__init__.py
cms_client/models/annotation.py
cms_client/models/bearer_response.py
cms_client/models/detail.py
cms_client/models/error_model.py
cms_client/models/http_validation_error.py
cms_client/models/input.py
cms_client/models/model_card.py
cms_client/models/model_type.py
cms_client/models/open_ai_chat_request.py
cms_client/models/open_ai_embeddings_request.py
cms_client/models/prompt_message.py
cms_client/models/prompt_role.py
cms_client/models/text_with_annotations.py
cms_client/models/text_with_public_key.py
cms_client/models/validation_error.py
cms_client/models/validation_error_loc_inner.py
test/test_annotation.py
test/test_annotations_api.py
test/test_authentication_api.py
test/test_bearer_response.py
test/test_detail.py
test/test_error_model.py
test/test_evaluating_api.py
test/test_generate_text_based_on_the_input_prompt_api.py
test/test_generative_api.py
test/test_http_validation_error.py
test/test_input.py
test/test_metadata_api.py
test/test_model_card.py
test/test_model_type.py
test/test_open_ai_chat_request.py
test/test_open_ai_compatible_api.py
test/test_open_ai_embeddings_request.py
test/test_prompt_message.py
test/test_prompt_role.py
test/test_redaction_api.py
test/test_rendering_api.py
test/test_text_with_annotations.py
test/test_text_with_public_key.py
test/test_training_api.py
test/test_validation_error.py
